{"cameraMode":{"drawMode":0,"name":"Shaded","section":"Shading Mode"},"sceneLighting":true,"audioPlay":false,"sceneViewState":{"m_AlwaysRefresh":false,"showFog":true,"showSkybox":true,"showFlares":true,"showImageEffects":true,"showParticleSystems":true,"showVisualEffectGraphs":true,"m_FxEnabled":true},"in2DMode":false,"pivot":{"x":-14.372758865356446,"y":-10.726871490478516,"z":-9.757494926452637},"rotation":{"x":-0.010364803485572338,"y":-0.9625552296638489,"z":0.26827624440193179,"w":-0.037283677607774737},"size":36.11598587036133,"orthographic":false}